hvsrpy/__init__.py
hvsrpy/cli.py
hvsrpy/constants.py
hvsrpy/data_wrangler.py
hvsrpy/frequency_amplitude_curve.py
hvsrpy/hvsr_azimuthal.py
hvsrpy/hvsr_curve.py
hvsrpy/hvsr_diffuse_field.py
hvsrpy/hvsr_geopsy.py
hvsrpy/hvsr_spatial.py
hvsrpy/hvsr_traditional.py
hvsrpy/instrument_response.py
hvsrpy/interact.py
hvsrpy/metadata.py
hvsrpy/object_io.py
hvsrpy/postprocessing.py
hvsrpy/preprocessing.py
hvsrpy/processing.py
hvsrpy/psd.py
hvsrpy/regex.py
hvsrpy/seismic_recording_3c.py
hvsrpy/sesame.py
hvsrpy/settings.py
hvsrpy/smoothing.py
hvsrpy/statistics.py
hvsrpy/timeseries.py
hvsrpy/window_rejection.py
hvsrpy-2.1.0.dist-info/licenses/LICENSE.txt
hvsrpy-2.1.0.dist-info/METADATA
hvsrpy-2.1.0.dist-info/WHEEL
hvsrpy-2.1.0.dist-info/entry_points.txt
hvsrpy-2.1.0.dist-info/top_level.txt
hvsrpy-2.1.0.dist-info/RECORD
