Metadata-Version: 2.4
Name: hvsrpy
Version: 2.1.0
Summary: A Python package for horizontal-to-vertical spectral ratio processing
Home-page: https://github.com/jpvantassel/hvsrpy
Author: Joseph P. Vantassel
Author-email: joseph.p.vantassel@gmail.com
Project-URL: Bug Reports, https://github.com/jpvantassel/hvsrpy/issues
Project-URL: Source, https://github.com/jpvantassel/hvsrpy
Project-URL: Docs, https://hvsrpy.readthedocs.io/en/latest/?badge=latest
Keywords: horizontal-to-vertical spectral ratio hv hvsr
Classifier: Development Status :: 5 - Production/Stable
Classifier: Intended Audience :: Developers
Classifier: Intended Audience :: Education
Classifier: Intended Audience :: Science/Research
Classifier: Topic :: Education
Classifier: Topic :: Scientific/Engineering
Classifier: Topic :: Scientific/Engineering :: Physics
Classifier: License :: OSI Approved :: GNU General Public License v3 or later (GPLv3+)
Classifier: Programming Language :: Python :: 3.8
Classifier: Programming Language :: Python :: 3.9
Classifier: Programming Language :: Python :: 3.10
Classifier: Programming Language :: Python :: 3.11
Classifier: Programming Language :: Python :: 3.12
Classifier: Programming Language :: Python :: 3.13
Requires-Python: >=3.8
License-File: LICENSE.txt
Requires-Dist: numpy>=1.22
Requires-Dist: scipy
Requires-Dist: obspy
Requires-Dist: pandas
Requires-Dist: shapely
Requires-Dist: termcolor
Requires-Dist: matplotlib
Requires-Dist: click>8.0.0
Requires-Dist: numba
Requires-Dist: scikit-learn
Provides-Extra: dev
Requires-Dist: tox; extra == "dev"
Requires-Dist: jupyterlab; extra == "dev"
Requires-Dist: coverage; extra == "dev"
Requires-Dist: sphinx; extra == "dev"
Requires-Dist: sphinx_rtd_theme; extra == "dev"
Requires-Dist: sphinx-click; extra == "dev"
Requires-Dist: autopep8; extra == "dev"
Dynamic: author
Dynamic: author-email
Dynamic: classifier
Dynamic: description
Dynamic: description-content-type
Dynamic: home-page
Dynamic: keywords
Dynamic: license-file
Dynamic: project-url
Dynamic: provides-extra
Dynamic: requires-dist
Dynamic: requires-python
Dynamic: summary
